[
  {
    "id": 1049,
    "date": "2026-01-14T01:09:48+00:00",
    "sender_id": 5173753598,
    "sender_name": "Nhat Nguyen",
    "text": "Dạ em xin phép thầy và anh chị cho em lên trễ tầm 15p ạ"
  },
  {
    "id": 1048,
    "date": "2026-01-13T23:47:03+00:00",
    "sender_id": 1074908741,
    "sender_name": "Tuan Thanh",
    "text": "Ok giữ sk nha"
  },
  {
    "id": 1047,
    "date": "2026-01-13T23:11:11+00:00",
    "sender_id": 6613489311,
    "sender_name": "Tín Lữ",
    "text": "Em xin phép thầy và anh chị cho em xin phép làm remote hôm nay (14/1) do em bị sốt ạ"
  },
  {
    "id": 1043,
    "date": "2026-01-13T01:38:34+00:00",
    "sender_id": 6674698522,
    "sender_name": "Thu Nguyen",
    "text": "Dạ em xin phép lên trễ tí do hôm qua em lỡ thức trễ nên em ngủ quên ạ"
  },
  {
    "id": 1042,
    "date": "2026-01-13T00:41:17+00:00",
    "sender_id": 6738609487,
    "sender_name": "Nguyễn Duy Thắng",
    "text": "Dạ em xin phép thầy và anh chị cho em lên trễ tầm 10h ạ, do có việc cá nhân ạ"
  },
  {
    "id": 1034,
    "date": "2026-01-12T03:57:20+00:00",
    "sender_id": 1111742807,
    "sender_name": "Huyền Khanh",
    "text": "rồi chiều có lên ko @KienLDG"
  },
  {
    "id": 1033,
    "date": "2026-01-12T01:56:59+00:00",
    "sender_id": 6674698522,
    "sender_name": "Thu Nguyen",
    "text": "Dạ lúc đầu em định xin lên trễ một chút mà do giờ em không có xe để đi nên em xin sáng nay cho em remote, trưa em lên vp lại ạ"
  },
  {
    "id": 1032,
    "date": "2026-01-12T01:32:48+00:00",
    "sender_id": 6674698522,
    "sender_name": "Thu Nguyen",
    "text": "Em xin phép lên trễ một chút ạ"
  },
  {
    "id": 1031,
    "date": "2026-01-12T01:06:08+00:00",
    "sender_id": 7942023665,
    "sender_name": "Kienldg",
    "text": "Em xin phép thầy với anh chị cho em off buổi sáng do em có việc cá nhân đột xuất ạ"
  },
  {
    "id": 1030,
    "date": "2026-01-11T14:39:11+00:00",
    "sender_id": 1111742807,
    "sender_name": "Huyền Khanh",
    "text": "Ok em"
  }
]